tidygrad/__init__.py
tidygrad/_modidx.py
tidygrad/functional.py
tidygrad/tensor.py
tidygrad/utils/__init__.py
tidygrad/utils/datasets.py
tidygrad/utils/grad_check.py
tidygrad-0.0.1.dist-info/LICENSE
tidygrad-0.0.1.dist-info/METADATA
tidygrad-0.0.1.dist-info/WHEEL
tidygrad-0.0.1.dist-info/entry_points.txt
tidygrad-0.0.1.dist-info/top_level.txt
tidygrad-0.0.1.dist-info/RECORD
