Metadata-Version: 2.1
Name: tidygrad
Version: 0.0.1
Summary: A tidy library for gradient-based optimization
Home-page: https://github.com/xl0/tidygrad
Author: Alexey
Author-email: alexey.zaytsev@gmail.com
License: MIT License
Keywords: nbdev jupyter notebook python
Classifier: Development Status :: 4 - Beta
Classifier: Intended Audience :: Developers
Classifier: Natural Language :: English
Classifier: Programming Language :: Python :: 3.7
Classifier: Programming Language :: Python :: 3.8
Classifier: Programming Language :: Python :: 3.9
Classifier: Programming Language :: Python :: 3.10
Classifier: License :: OSI Approved :: MIT License
Requires-Python: >=3.7
License-File: LICENSE
Requires-Dist: numpy
Provides-Extra: dev
Requires-Dist: black ; extra == 'dev'
Requires-Dist: nbdev ; extra == 'dev'
Requires-Dist: matplotlib ; extra == 'dev'
Requires-Dist: lovely-numpy ; extra == 'dev'
Requires-Dist: requests ; extra == 'dev'
